{
  "project_info": {
    "project_number": "479848984157",
    "firebase_url": "https://gamechat-2ec25.firebaseio.com",
    "project_id": "gamechat-2ec25",
    "storage_bucket": "gamechat-2ec25.appspot.com"
  },
  "client": [
    {
      "client_info": {
        "mobilesdk_app_id": "1:479848984157:android:5a3f6677acbb6b17",
        "android_client_info": {
          "package_name": "magic.com.gamechat"
        }
      },
      "oauth_client": [
        {
          "client_id": "479848984157-fi5u8a6rirkqeahlcstr0gt4r5qqcrhb.apps.googleusercontent.com",
          "client_type": 1,
          "android_info": {
            "package_name": "magic.com.gamechat",
            "certificate_hash": "D9AC0669CACC0CA152E3ADA646A1F53134EFEF96"
          }
        },
        {
          "client_id": "479848984157-qmfquisep9pi6qj7vn290tsb7ut8fse1.apps.googleusercontent.com",
          "client_type": 3
        }
      ],
      "api_key": [
        {
          "current_key": "AIzaSyB3YZ_lI_bJr2ihQgfeWuE-SC6LXNRVLLw"
        }
      ],
      "services": {
        "analytics_service": {
          "status": 1
        },
        "appinvite_service": {
          "status": 2,
          "other_platform_oauth_client": [
            {
              "client_id": "479848984157-qmfquisep9pi6qj7vn290tsb7ut8fse1.apps.googleusercontent.com",
              "client_type": 3
            }
          ]
        },
        "ads_service": {
          "status": 2
        }
      }
    }
  ],
  "configuration_version": "1"
}